.long-description.html
README.rst
setup.py
src/collective/__init__.py
src/collective.cart.core.egg-info/PKG-INFO
src/collective.cart.core.egg-info/SOURCES.txt
src/collective.cart.core.egg-info/dependency_links.txt
src/collective.cart.core.egg-info/entry_points.txt
src/collective.cart.core.egg-info/namespace_packages.txt
src/collective.cart.core.egg-info/not-zip-safe
src/collective.cart.core.egg-info/requires.txt
src/collective.cart.core.egg-info/top_level.txt
src/collective/cart/__init__.py
src/collective/cart/core/__init__.py
src/collective/cart/core/configure.zcml
src/collective/cart/core/content.py
src/collective/cart/core/event.py
src/collective/cart/core/interfaces.py
src/collective/cart/core/schema.py
src/collective/cart/core/session.py
src/collective/cart/core/subscriber.py
src/collective/cart/core/upgrades.py
src/collective/cart/core/upgrades.zcml
src/collective/cart/core/validator.py
src/collective/cart/core/adapter/__init__.py
src/collective/cart/core/adapter/article.py
src/collective/cart/core/adapter/configure.zcml
src/collective/cart/core/adapter/interface.py
src/collective/cart/core/adapter/order.py
src/collective/cart/core/adapter/order_container.py
src/collective/cart/core/browser/__init__.py
src/collective/cart/core/browser/configure.zcml
src/collective/cart/core/browser/interfaces.py
src/collective/cart/core/browser/miscellaneous.py
src/collective/cart/core/browser/view.py
src/collective/cart/core/browser/viewlet.py
src/collective/cart/core/browser/static/article.png
src/collective/cart/core/browser/static/cart.png
src/collective/cart/core/browser/viewlets/add-to-cart.pt
src/collective/cart/core/browser/viewlets/cart-article-listing.pt
src/collective/cart/core/browser/viewlets/order-article-listing.pt
src/collective/cart/core/browser/viewlets/order-listing.pt
src/collective/cart/core/docs/CONTRIBUTORS.rst
src/collective/cart/core/docs/CREDITS.rst
src/collective/cart/core/docs/HISTORY.rst
src/collective/cart/core/docs/LICENSE.rst
src/collective/cart/core/locales/collective.cart.core.pot
src/collective/cart/core/locales/fi/LC_MESSAGES/collective.cart.core.mo
src/collective/cart/core/locales/fi/LC_MESSAGES/collective.cart.core.po
src/collective/cart/core/locales/fi/LC_MESSAGES/plone.mo
src/collective/cart/core/locales/fi/LC_MESSAGES/plone.po
src/collective/cart/core/portlets/__init__.py
src/collective/cart/core/portlets/cart.pt
