Metadata-Version: 1.1
Name: collective.cart.core
Version: 0.8
Summary: Yet another cart for Plone.
Home-page: https://github.com/collective/collective.cart.core/
Author: Taito Horiuchi
Author-email: taito.horiuchi@gmail.com
License: BSD
Platform: UNKNOWN
Classifier: Framework :: Plone
Classifier: Framework :: Plone :: 4.3
Classifier: License :: OSI Approved :: BSD License
Classifier: Programming Language :: Python
Classifier: Programming Language :: Python :: 2.7
